iocursor-0.1.4.dist-info/top_level.txt
iocursor-0.1.4.dist-info/WHEEL
iocursor-0.1.4.dist-info/COPYING
iocursor-0.1.4.dist-info/RECORD
iocursor-0.1.4.dist-info/METADATA
iocursor/cursor.h
iocursor/py.typed
iocursor/cursor.pyi
iocursor/cursor.c
iocursor/__init__.py
iocursor/cursor.cpython-310-x86_64-linux-gnu.so
