Metadata-Version: 2.1
Name: iocursor
Version: 0.1.4
Summary: A zero-copy file-like wrapper for byte buffers, inspired by Rust's std::io::Cursor.
Home-page: https://github.com/althonos/iocursor
Author: Martin Larralde
Author-email: martin.larralde@embl.de
License: MIT
Project-URL: Bug Tracker, https://github.com/althonos/iocursor/issues
Project-URL: Builds, https://github.com/althonos/iocursor/actions
Project-URL: Coverage, https://codecov.io/gh/althonos/iocursor
Project-URL: Changelog, https://github.com/althonos/iocursor/blob/master/CHANGELOG.md
Keywords: io,buffer,file-like,cursor
Platform: any
Classifier: Development Status :: 4 - Beta
Classifier: Intended Audience :: Developers
Classifier: License :: OSI Approved :: MIT License
Classifier: Operating System :: OS Independent
Classifier: Programming Language :: C
Classifier: Programming Language :: Python
Classifier: Programming Language :: Python :: 3 :: Only
Classifier: Programming Language :: Python :: 3.5
Classifier: Programming Language :: Python :: 3.6
Classifier: Programming Language :: Python :: 3.7
Classifier: Programming Language :: Python :: 3.8
Classifier: Programming Language :: Python :: 3.9
Classifier: Programming Language :: Python :: 3.10
Classifier: Programming Language :: Python :: 3.11
Classifier: Programming Language :: Python :: Implementation :: PyPy
Classifier: Programming Language :: Python :: Implementation :: CPython
Classifier: Topic :: Software Development :: Libraries :: Python Modules
Classifier: Topic :: Utilities
Classifier: Typing :: Typed
Requires-Python: >=3.5
